auto_metamask2/__init__.py
auto_metamask2/__version__.py
auto_metamask2/core.py
auto_metamask2-2.0.0.dist-info/LICENSE
auto_metamask2-2.0.0.dist-info/METADATA
auto_metamask2-2.0.0.dist-info/WHEEL
auto_metamask2-2.0.0.dist-info/top_level.txt
auto_metamask2-2.0.0.dist-info/RECORD
