Metadata-Version: 2.1
Name: auto-metamask2
Version: 2.0.0
Summary: Web3 automation testing tool.
Home-page: https://github.com/miklisanton/auto-metamask
Author: aimkiray+zavropod
Author-email: root@meowwoo.com
License: MIT
Classifier: License :: OSI Approved :: MIT License
Classifier: Programming Language :: Python
Classifier: Programming Language :: Python :: 3
Classifier: Programming Language :: Python :: 3.6
Classifier: Programming Language :: Python :: Implementation :: CPython
Classifier: Programming Language :: Python :: Implementation :: PyPy
Requires-Python: >=3.6.0
License-File: LICENSE
Requires-Dist: selenium-stealth>=1.0.6
Requires-Dist: selenium>=4.2.0
Requires-Dist: webdriver-manager>=3.7.0
